gym_sapientino/__init__.py
gym_sapientino/__main__.py
gym_sapientino/assets/.gitkeep
gym_sapientino/core/__init__.py
gym_sapientino/core/configurations.py
gym_sapientino/core/constants.py
gym_sapientino/core/objects.py
gym_sapientino/core/states.py
gym_sapientino/core/types.py
gym_sapientino/play.py
gym_sapientino/rendering/__init__.py
gym_sapientino/rendering/base.py
gym_sapientino/rendering/pygame.py
gym_sapientino/sapientino_env.py
gym_sapientino/utils.py
gym_sapientino/wrappers/__init__.py
gym_sapientino/wrappers/dict_space.py
gym_sapientino-0.2.0.dist-info/LICENSE
gym_sapientino-0.2.0.dist-info/WHEEL
gym_sapientino-0.2.0.dist-info/METADATA
gym_sapientino-0.2.0.dist-info/RECORD
