Metadata-Version: 2.1
Name: gym-sapientino
Version: 0.2.0
Summary: Gym Sapientino environment using Pygame.
Home-page: https://whitemech.github.io/gym-sapientino
License: GPL-3.0-or-later
Keywords: sapientino,reinforcement learning,openai gym
Author: Marco Favorito
Author-email: favorito@diag.uniroma1.it
Requires-Python: >=3.7,<4.0
Classifier: Development Status :: 2 - Pre-Alpha
Classifier: Intended Audience :: Developers
Classifier: License :: OSI Approved :: GNU General Public License v3 or later (GPLv3+)
Classifier: Natural Language :: English
Classifier: Programming Language :: Python :: 3
Classifier: Programming Language :: Python :: 3.7
Classifier: Programming Language :: Python :: 3.8
Requires-Dist: gym (>=0.17.2,<0.18.0)
Requires-Dist: matplotlib (>=3.3.2,<4.0.0)
Requires-Dist: numpy (>=1.19.2,<2.0.0)
Requires-Dist: pandas (>=1.1.2,<2.0.0)
Requires-Dist: pygame (>=2.0.0.dev6)
Requires-Dist: seaborn (>=0.11.0,<0.12.0)
Project-URL: Bug Tracker, https://github.com/whitemech/gym-sapientino/issues
Project-URL: Documentation, https://whitemech.github.io/gym-sapientino
Project-URL: Pull Requests, https://github.com/whitemech/gym-sapientino/pulls
Project-URL: Repository, https://github.com/whitemech/gym-sapientino.git
